api/__init__.py
api/artifact.py
api/azure_utils.py
api/generator.py
api/rest_api.py
api/ui_app.py
api_automation_kit-0.7.0.dist-info/METADATA
api_automation_kit-0.7.0.dist-info/WHEEL
api_automation_kit-0.7.0.dist-info/top_level.txt
api_automation_kit-0.7.0.dist-info/RECORD
