Metadata-Version: 2.1
Name: api-automation-kit
Version: 0.7.0
Summary: api-automation-kit-package (beta version)
Home-page: https://upload.pypi.org/legacy/
Author: Automation Team
Author-email: automation.team@automation.co.il
License: MIT
Platform: UNKNOWN
Classifier: Programming Language :: Python :: 3
Classifier: License :: OSI Approved :: MIT License
Classifier: Operating System :: OS Independent
Requires-Python: >=3.8
Requires-Dist: allure-pytest (~=2.9.43)
Requires-Dist: allure-python-commons (~=2.9.43)
Requires-Dist: setuptools
Requires-Dist: genson (~=1.2.2)
Requires-Dist: artifacts-keyring (~=0.3.1)
Requires-Dist: twine (~=3.4.2)
Requires-Dist: wheel (~=0.37.0)
Requires-Dist: pandas (~=1.3.3)
Requires-Dist: streamlit (~=1.0.0)
Requires-Dist: locust (~=2.2.3)
Requires-Dist: requests (~=2.26.0)
Requires-Dist: azure-devops (==6.0.0b4)
Requires-Dist: xmltojson (~=0.2.0)
Requires-Dist: msrest (~=0.6.21)
Requires-Dist: utils (~=1.0.1)
